ezudesign/__init__.py
ezudesign/configuration.py
ezudesign/eventhub.py
ezudesign/taskflow.py
ezudesign/taskpool.py
ezudesign/tasksequence.py
ezudesign/utils.py
ezudesign-0.4.2.dist-info/LICENSE
ezudesign-0.4.2.dist-info/METADATA
ezudesign-0.4.2.dist-info/WHEEL
ezudesign-0.4.2.dist-info/top_level.txt
ezudesign-0.4.2.dist-info/RECORD
