Metadata-Version: 2.1
Name: ezudesign
Version: 0.4.2
Summary: Some usability designs.
Home-page: https://github.com/numlinka/pyezudesign
Author: numlinka
Author-email: numlinka@163.com
License: LGPLv3
Keywords: sample
Classifier: License :: OSI Approved :: GNU Lesser General Public License v3 (LGPLv3)
Classifier: Programming Language :: Python :: 3
License-File: LICENSE
Requires-Dist: typex>=0.3.0
